jconfigpy/Config.py
jconfigpy/Dialog.py
jconfigpy/ErrorType.py
jconfigpy/Item.py
jconfigpy/Recipe.py
jconfigpy/VariableMonitor.py
jconfigpy/__init__.py
jconfigpy/__main__.py
jconfigpy-0.1.9.dist-info/DESCRIPTION.rst
jconfigpy-0.1.9.dist-info/METADATA
jconfigpy-0.1.9.dist-info/RECORD
jconfigpy-0.1.9.dist-info/WHEEL
jconfigpy-0.1.9.dist-info/metadata.json
jconfigpy-0.1.9.dist-info/top_level.txt
