Metadata-Version: 2.0
Name: jconfigpy
Version: 0.1.9
Summary: configuration utility which easily integrated into project using gnu make as build system
Home-page: http://github.com/fritzprix/jconfigpy
Author: fritzprix
Author-email: innocentevil0914@gmail.com
License: BSD
Download-URL: http://github.com/fritzprix/jconfigpy/archive/0.1.9.tar.gz
Keywords: configuration utility make
Platform: UNKNOWN
Classifier: Development Status :: 3 - Alpha
Classifier: Topic :: Utilities
Classifier: License :: OSI Approved :: BSD License
